LICENSE
MANIFEST.in
README.md
setup.py
rsxpy/__init__.py
rsxpy/builder.py
rsxpy/core.py
rsxpy/icon.ico
rsxpy/icon.png
rsxpy/icon_alternative.ico
rsxpy/icon_alternative.png
rsxpy/logo.png
rsxpy/rsxgen.py
rsxpy/rsxlib.py
rsxpy/std.py
rsxpy/tools.py
rsxpy.egg-info/PKG-INFO
rsxpy.egg-info/SOURCES.txt
rsxpy.egg-info/dependency_links.txt
rsxpy.egg-info/entry_points.txt
rsxpy.egg-info/requires.txt
rsxpy.egg-info/top_level.txt
rsxpy/include/rsxbuild/init.rsxc
rsxpy/include/rsxbuild/init.rsxh
rsxpy/include/rsxbuild/rsxbuild.py
rsxpy/include/rsxf/init.rsxc
rsxpy/include/rsxf/init.rsxh
rsxpy/include/rsxf/rsxf.py
rsxpy/include/rsxgui/init.rsxc
rsxpy/include/rsxgui/init.rsxh
rsxpy/include/rsxgui/messagebox.py
rsxpy/include/rsxgui/rsxgui.py
rsxpy/include/rsxio/init.rsxc
rsxpy/include/rsxio/init.rsxh
rsxpy/include/rsxio/rsxio.py
rsxpy/include/rsxmath/init.rsxc
rsxpy/include/rsxmath/init.rsxh
rsxpy/include/rsxmath/rsxmath.py
rsxpy/include/rsxmixer/init.rsxc
rsxpy/include/rsxmixer/init.rsxh
rsxpy/include/rsxmixer/rsxmixer.py
rsxpy/include/rsxos/init.rsxc
rsxpy/include/rsxos/init.rsxh
rsxpy/include/rsxos/rsxos.py
rsxpy/include/rsxrand/init.rsxc
rsxpy/include/rsxrand/init.rsxh
rsxpy/include/rsxrand/rsxrand.py
rsxpy/include/rsxraylib/audio.py
rsxpy/include/rsxraylib/colors.py
rsxpy/include/rsxraylib/consts.rsxc
rsxpy/include/rsxraylib/consts.rsxh
rsxpy/include/rsxraylib/core.py
rsxpy/include/rsxraylib/extras.py
rsxpy/include/rsxraylib/globals.py
rsxpy/include/rsxraylib/init.rsxc
rsxpy/include/rsxraylib/init.rsxh
rsxpy/include/rsxraylib/models.py
rsxpy/include/rsxraylib/shapes.py
rsxpy/include/rsxraylib/structs.py
rsxpy/include/rsxraylib/text.py
rsxpy/include/rsxraylib/textures.py
rsxpy/include/rsxsdl2/constants.rsxc
rsxpy/include/rsxsdl2/constants.rsxh
rsxpy/include/rsxsdl2/globals.py
rsxpy/include/rsxsdl2/init.rsxc
rsxpy/include/rsxsdl2/init.rsxh
rsxpy/include/rsxsdl2/rsxsdl2.py
rsxpy/include/rsxsocket/constants.rsxc
rsxpy/include/rsxsocket/constants.rsxh
rsxpy/include/rsxsocket/init.rsxc
rsxpy/include/rsxsocket/init.rsxh
rsxpy/include/rsxsocket/rsxsocket.py
rsxpy/include/rsxsocket/sockets.py
rsxpy/include/rsxstd/init.rsxc
rsxpy/include/rsxstd/init.rsxh
