Metadata-Version: 2.1
Name: rsxpy
Version: 0.1.1
Summary: An interpreted statically typed multi paradigm general purpose programming language designed for cross platform applications.
Home-page: https://github.com/Aermoss/RSX
Author: Yusuf Rencber
Author-email: aermoss.0@gmail.com
License: MIT
Platform: UNKNOWN
License-File: LICENSE
